README.md
setup.py
pythonic_xray/__init__.py
pythonic_xray/__main__.py
pythonic_xray/code_analyzer.py
pythonic_xray/main.py
pythonic_xray.egg-info/PKG-INFO
pythonic_xray.egg-info/SOURCES.txt
pythonic_xray.egg-info/dependency_links.txt
pythonic_xray.egg-info/entry_points.txt
pythonic_xray.egg-info/top_level.txt