Metadata-Version: 2.4
Name: pythonic-xray
Version: 0.7
Home-page: https://github.com/M-106/Pythonic-X-ray
Author: Tobia Ippolito
License: MIT
Classifier: Programming Language :: Python :: 3
Classifier: Operating System :: OS Independent
Dynamic: author
Dynamic: classifier
Dynamic: description
Dynamic: description-content-type
Dynamic: home-page
Dynamic: license
